mathbyaarushlohit/__init__.py
mathbyaarushlohit/mathbyaarushlohit.py
mathbyaarushlohit-0.7.dist-info/licenses/LICENSE
mathbyaarushlohit-0.7.dist-info/METADATA
mathbyaarushlohit-0.7.dist-info/WHEEL
mathbyaarushlohit-0.7.dist-info/top_level.txt
mathbyaarushlohit-0.7.dist-info/RECORD
