Metadata-Version: 2.4
Name: mathbyaarushlohit
Version: 0.7
Summary: A small package to help biology-background students and coding slow learners with this math module Contains all Math Practical program.
Author: Lohit (A.K.A AarushLohit)
License-File: LICENSE
Requires-Dist: numpy
Dynamic: author
Dynamic: license-file
Dynamic: requires-dist
Dynamic: summary
